{"next_url": "http://startpage.wandoujia.com/five/v3/tabs/tops?start=260&max=5&sessionId=7598048721385334827&pos=m%2Ftops","pre_url": "http://startpage.wandoujia.com/five/v3/tabs/tops?start=250&max=5&sessionId=7598048721385334827&pos=m%2Ftops","has_more": true,"pb_version": 0,"session_id": 7598048721385334827,"status": 200,"entity": [{"icon": "http://img.wdjimg.com/mms/icon/v1/6/0f/0cbcd00aca42a1ebf1d55d2c1f5ef0f6_256_256.png","title": "神雕侠侣","sub_title": "245.7MB","detail": {"app_detail": {"ad": false,"detail_param": "pos=m%2Ftops%2FClassicTopsPage%2FAppGameRankWithNumber%2FAPP&udid=","apk": [{"ads_type": "NONE","beta": false,"bytes_": 257643059,"download_url": {"aggr_weight": 300,"market": "官方","refer_url": "http://apps.wandoujia.com/apps/com.wanmei.mini.condor.wdj?uid=10522396","url": "http://apps.wandoujia.com/redirect?signature=8c9df16&url=http%3A%2F%2Fapk.wandoujia.com%2Ff%2F94%2F2a1863744fcaae381b999494318b594f.apk&pn=com.wanmei.mini.condor.wdj&md5=2a1863744fcaae381b999494318b594f&apkid=18761330&vc=71&size=257643059&pos=m%2Ftops%2FClassicTopsPage%2FAppGameRankWithNumber%2FAPP&udid="},"size": "245.71M","version_code": 71,"version_name": "1.7.1","security_status": "UNKNOWN","md5": "2a1863744fcaae381b999494318b594f","resolution": ["mdpi","hdpi"],"permission_level": "TRUSTED","verified": 2,"superior": 0,"compatible": 1,"paid_type": "NONE","creation": 1467345557000}],"title": "神雕侠侣","comments_count": 3281,"likes_count": 2802,"dislikes_count": 1328,"editor_comment": "金庸大师唯一授权的正版回合制手游。唯美爱情再现！携手杨过、小龙女一起快意江湖！","installed_count_str": "64 万","package_name": "com.wanmei.mini.condor.wdj","id": 705529,"likes_rate": 68,"banner": "http://img.wdjimg.com/mms/banner/5/7e/bedb68e5a3399d81abb61d59ac1637e5_300_250.jpeg","updated_date": 1467351190000,"app_type": "GAME","developer": {"id": 10522396,"name": "完美世界（重庆）互动科技有限公司"},"icons": {"px24": "http://img.wdjimg.com/mms/icon/v1/6/0f/0cbcd00aca42a1ebf1d55d2c1f5ef0f6_24_24.png","px36": "http://img.wdjimg.com/mms/icon/v1/6/0f/0cbcd00aca42a1ebf1d55d2c1f5ef0f6_36_36.png","px48": "http://img.wdjimg.com/mms/icon/v1/6/0f/0cbcd00aca42a1ebf1d55d2c1f5ef0f6_48_48.png","px68": "http://img.wdjimg.com/mms/icon/v1/6/0f/0cbcd00aca42a1ebf1d55d2c1f5ef0f6_68_68.png","px78": "http://img.wdjimg.com/mms/icon/v1/6/0f/0cbcd00aca42a1ebf1d55d2c1f5ef0f6_78_78.png","px100": "http://img.wdjimg.com/mms/icon/v1/6/0f/0cbcd00aca42a1ebf1d55d2c1f5ef0f6_100_100.png","px256": "http://img.wdjimg.com/mms/icon/v1/6/0f/0cbcd00aca42a1ebf1d55d2c1f5ef0f6_256_256.png"},"categories": [{"alias": "rpg","level": 1,"name": "角色扮演","type": "GAME"},{"alias": "ol","level": 1,"name": "网络游戏","type": "GAME"}],"title_en": ""}},"action": {"intent": "wdj://games/com.wanmei.mini.condor.wdj?pageName=ClassicTopsPage&cardName=AppGameRankWithNumber&feedItemId=com.wanmei.mini.condor.wdj","url": "http://apis.wandoujia.com/five/v2/apps/com.wanmei.mini.condor.wdj?pos=m%2Ftops%2FClassicTopsPage%2FAppGameRankWithNumber%2FAPP&udid="},"badge": 256,"symbol": "255.","content_type": "APP","template_type": "SINGLE_TALL","id_string": "AppGameRankWithNumber:com.wanmei.mini.condor.wdj","tag_line": "245.7MB","icon_image": {"url": "http://img.wdjimg.com/mms/icon/v1/6/0f/0cbcd00aca42a1ebf1d55d2c1f5ef0f6_256_256.png","rgbs": -14189605},"strategy_name": "ClassicTopsPage"},{"icon": "http://img.wdjimg.com/mms/icon/v1/1/d7/b0cea17af19e00d31901492fd2f41d71_256_256.png","title": "金山彩票","sub_title": "9.1MB","detail": {"app_detail": {"ad": true,"detail_param": "isAds=true&token=nNooOu0_aG2HSOxMDllaeYoSfUs_GbuLfx2Y9qV564TM8fJ6IGQ_-U_DhGkuso6A0aSiBWZTS2zwQ_yAy9oBSQ&adsPos=packageAds%2F/0&source=&sid=0dbb24fb148647ebb1b0d91cfe9892f21470310992181&sToken=X3PBguDqu4ND81F3svZ57nHQ_wTwG3mU8U7AM-k5t9Esi3Cf0fzpqGUQSKH8R8dict2luSdLDrPDQ6KsLOjOEw&bucketId=bi-plutus-cnc5.hlg01.wandoujia.com&testTag=plutus&adwordId=19&pn=com.cwvs.jdd&bid=1434486&isAds=true&pos=m%2Ftops%2FClassicTopsPage%2FAppGameRankWithNumber%2FAPP&udid=","apk": [{"ads_type": "NONE","beta": false,"bytes_": 9495977,"download_url": {"aggr_weight": 2,"market": "360手机助手","refer_url": "http://123.125.82.206/mintf/getAppInfoByIds?pname=com.cwvs.jdd","url": "http://apps.wandoujia.com/redirect?signature=58d3683&url=http%3A%2F%2Fm.shouji.360tpcdn.com%2F160803%2F4d70bb36e93c2e71689f7f7a739eee7e%2Fcom.cwvs.jdd_357.apk&pn=com.cwvs.jdd&md5=4d70bb36e93c2e71689f7f7a739eee7e&apkid=19081238&vc=357&size=9495977&pos=m%2Ftops%2FClassicTopsPage%2FAppGameRankWithNumber%2FAPP&udid="},"size": "9.06M","version_code": 357,"version_name": "3.5.7","security_status": "UNKNOWN","md5": "4d70bb36e93c2e71689f7f7a739eee7e","resolution": ["ldpi","mdpi","hdpi","xhdpi","xxhdpi"],"permission_level": "TRUSTED","verified": 2,"superior": 0,"compatible": 1,"paid_type": "NONE","creation": 1470218153000}],"title": "金山彩票","comments_count": 25,"likes_count": 26,"dislikes_count": 15,"editor_comment": "新人注册送 10 元，每月签到还有钱拿。梦想还是要有的，万一中了呢？","installed_count_str": "19 万","package_name": "com.cwvs.jdd","id": 268707,"likes_rate": 63,"banner": "http://img.wdjimg.com/mms/banner/a/52/ea775002427284aaa4dfa3a09667c52a_300_250.jpeg","updated_date": 1470218246000,"impr_url": "http://click.wandoujia.com/static/uploads/i/com.cwvs.jdd/39120/1434486.gif?bid=1434486&adsPos=packageAds%2F/0&source=&sid=0dbb24fb148647ebb1b0d91cfe9892f21470310992181&sToken=X3PBguDqu4ND81F3svZ57nHQ_wTwG3mU8U7AM-k5t9Esi3Cf0fzpqGUQSKH8R8dict2luSdLDrPDQ6KsLOjOEw&bucketId=bi-plutus-cnc5.hlg01.wandoujia.com&testTag=plutus&adwordId=19&pn=com.cwvs.jdd&token=nNooOu0_aG2HSOxMDllaeYoSfUs_GbuLfx2Y9qV564TM8fJ6IGQ_-U_DhGkuso6A0aSiBWZTS2zwQ_yAy9oBSQ&pos=m%2Ftops%2FClassicTopsPage%2FAppGameRankWithNumber%2FAPP","app_type": "APP","developer": {"id": 208076380,"name": "北京沁澜文化传媒有限公司"},"icons": {"px24": "http://img.wdjimg.com/mms/icon/v1/1/d7/b0cea17af19e00d31901492fd2f41d71_24_24.png","px36": "http://img.wdjimg.com/mms/icon/v1/1/d7/b0cea17af19e00d31901492fd2f41d71_36_36.png","px48": "http://img.wdjimg.com/mms/icon/v1/1/d7/b0cea17af19e00d31901492fd2f41d71_48_48.png","px68": "http://img.wdjimg.com/mms/icon/v1/1/d7/b0cea17af19e00d31901492fd2f41d71_68_68.png","px78": "http://img.wdjimg.com/mms/icon/v1/1/d7/b0cea17af19e00d31901492fd2f41d71_78_78.png","px100": "http://img.wdjimg.com/mms/icon/v1/1/d7/b0cea17af19e00d31901492fd2f41d71_100_100.png","px256": "http://img.wdjimg.com/mms/icon/v1/1/d7/b0cea17af19e00d31901492fd2f41d71_256_256.png"},"categories": [{"alias": "finance","level": 1,"name": "金融理财","type": "APP"},{"level": 2,"name": "彩票","type": "APP"}],"alias": "奖多多彩票 Android_com.cwvs.jdd"}},"action": {"intent": "wdj://apps/com.cwvs.jdd?pageName=ClassicTopsPage&cardName=AppGameRankWithNumber&feedItemId=com.cwvs.jdd","url": "http://apis.wandoujia.com/five/v2/apps/com.cwvs.jdd?isAds=true&token=nNooOu0_aG2HSOxMDllaeYoSfUs_GbuLfx2Y9qV564TM8fJ6IGQ_-U_DhGkuso6A0aSiBWZTS2zwQ_yAy9oBSQ&adsPos=packageAds%2F/0&source=&sid=0dbb24fb148647ebb1b0d91cfe9892f21470310992181&sToken=X3PBguDqu4ND81F3svZ57nHQ_wTwG3mU8U7AM-k5t9Esi3Cf0fzpqGUQSKH8R8dict2luSdLDrPDQ6KsLOjOEw&bucketId=bi-plutus-cnc5.hlg01.wandoujia.com&testTag=plutus&adwordId=19&pn=com.cwvs.jdd&bid=1434486&isAds=true&pos=m%2Ftops%2FClassicTopsPage%2FAppGameRankWithNumber%2FAPP&udid="},"badge": 288,"symbol": "256.","content_type": "APP","template_type": "SINGLE_TALL","id_string": "AppGameRankWithNumber:com.cwvs.jdd","tag_line": "9.1MB","icon_image": {"url": "http://img.wdjimg.com/mms/icon/v1/1/d7/b0cea17af19e00d31901492fd2f41d71_256_256.png","rgbs": -35981},"strategy_name": "ClassicTopsPage"},{"icon": "http://img.wdjimg.com/mms/icon/v1/e/b8/f573459f172aa7ffade6e8e7c74bcb8e_256_256.png","title": "Power Clean","sub_title": "3.0MB","detail": {"app_detail": {"ad": false,"detail_param": "pos=m%2Ftops%2FClassicTopsPage%2FAppGameRankWithNumber%2FAPP&udid=","apk": [{"ads_type": "EMBEDED","beta": false,"bytes_": 3183978,"download_url": {"aggr_weight": 2,"market": "360手机助手","refer_url": "http://123.125.82.206/mintf/getAppInfoByIds?pname=com.lionmobi.powerclean","url": "http://apps.wandoujia.com/redirect?signature=19d3669&url=http%3A%2F%2Fm.shouji.360tpcdn.com%2F160803%2F453e7e6d95c23d67f728413830687063%2Fcom.lionmobi.powerclean_143.apk&pn=com.lionmobi.powerclean&md5=453e7e6d95c23d67f728413830687063&apkid=19069474&vc=143&size=3183978&pos=m%2Ftops%2FClassicTopsPage%2FAppGameRankWithNumber%2FAPP&udid="},"size": "3.04M","version_code": 143,"version_name": "2.8.7.13","security_status": "UNKNOWN","md5": "453e7e6d95c23d67f728413830687063","resolution": ["ldpi","mdpi","hdpi","xhdpi","xxhdpi","xxxhdpi"],"permission_level": "NORMAL","verified": 3,"superior": 0,"compatible": 1,"paid_type": "NONE","creation": 1470107259000}],"title": "Power Clean","comments_count": 179,"likes_count": 178,"dislikes_count": 15,"installed_count_str": "17 万","package_name": "com.lionmobi.powerclean","id": 2471415,"likes_rate": 92,"banner": "http://img.wdjimg.com/mms/banner/1/11/a2d57d71f51c945d4115c18bbc49f111_300_250.jpeg","updated_date": 1470117847000,"app_type": "APP","developer": {"email": "contact@lionmobi.com","id": 206308950,"name": "成都狮之吼科技有限公司"},"icons": {"px24": "http://img.wdjimg.com/mms/icon/v1/e/b8/f573459f172aa7ffade6e8e7c74bcb8e_24_24.png","px36": "http://img.wdjimg.com/mms/icon/v1/e/b8/f573459f172aa7ffade6e8e7c74bcb8e_36_36.png","px48": "http://img.wdjimg.com/mms/icon/v1/e/b8/f573459f172aa7ffade6e8e7c74bcb8e_48_48.png","px68": "http://img.wdjimg.com/mms/icon/v1/e/b8/f573459f172aa7ffade6e8e7c74bcb8e_68_68.png","px78": "http://img.wdjimg.com/mms/icon/v1/e/b8/f573459f172aa7ffade6e8e7c74bcb8e_78_78.png","px100": "http://img.wdjimg.com/mms/icon/v1/e/b8/f573459f172aa7ffade6e8e7c74bcb8e_100_100.png","px256": "http://img.wdjimg.com/mms/icon/v1/e/b8/f573459f172aa7ffade6e8e7c74bcb8e_256_256.png"},"categories": [{"alias": "optimization","level": 1,"name": "系统工具","type": "APP"},{"level": 2,"name": "优化","type": "APP"}],"title_en": "Power Clean ","alias": "Power Clean - Optimize & Clean Android_com.lionmobi.powerclean"}},"action": {"intent": "wdj://apps/com.lionmobi.powerclean?pageName=ClassicTopsPage&cardName=AppGameRankWithNumber&feedItemId=com.lionmobi.powerclean","url": "http://apis.wandoujia.com/five/v2/apps/com.lionmobi.powerclean?pos=m%2Ftops%2FClassicTopsPage%2FAppGameRankWithNumber%2FAPP&udid="},"badge": 256,"symbol": "257.","content_type": "APP","template_type": "SINGLE_TALL","id_string": "AppGameRankWithNumber:com.lionmobi.powerclean","tag_line": "3.0MB","icon_image": {"url": "http://img.wdjimg.com/mms/icon/v1/e/b8/f573459f172aa7ffade6e8e7c74bcb8e_256_256.png"},"strategy_name": "ClassicTopsPage"},{"icon": "http://img.wdjimg.com/mms/icon/v1/1/c8/e1e9126c136e18399204a1b738262c81_256_256.png","title": "会说话的金杰","sub_title": "46.9MB","detail": {"app_detail": {"ad": false,"detail_param": "pos=m%2Ftops%2FClassicTopsPage%2FAppGameRankWithNumber%2FAPP&udid=","apk": [{"ads_type": "EMBEDED","beta": false,"bytes_": 49147176,"download_url": {"aggr_weight": 1,"market": "应用汇","refer_url": "http://www.appchina.com/app/com.outfit7.talkinggingerfree","url": "http://apps.wandoujia.com/redirect?signature=055db18&url=http%3A%2F%2Fwww.appchina.com%2Fmarket%2Fr%2F3394431%2Fcom.outfit7.talkinggingerfree_100.vapk%3Fc%3Daplus.direct%26m%3Dredirect%26p%3Daplus.detail%26page%3Dappplus.detail%26ref%26uid%3D0&pn=com.outfit7.talkinggingerfree&md5=9741a02892234cd0e0a06993f6c6d174&apkid=16366975&vc=100&size=49147176&pos=m%2Ftops%2FClassicTopsPage%2FAppGameRankWithNumber%2FAPP&udid="},"size": "46.87M","version_code": 100,"version_name": "2.3","security_status": "UNKNOWN","md5": "9741a02892234cd0e0a06993f6c6d174","resolution": ["ldpi","mdpi","hdpi","xhdpi","xxhdpi","xxxhdpi"],"permission_level": "NORMAL","verified": 3,"superior": 0,"compatible": 1,"paid_type": "NONE","creation": 1446456127000}],"title": "会说话的金杰","comments_count": 1191,"likes_count": 975,"dislikes_count": 217,"editor_comment": "Out Fit 7 Ltd.专门针对中国市场开发的版本，支持将视频分享到新浪、腾讯微博，或是优酷视频。","installed_count_str": "336 万","package_name": "com.outfit7.talkinggingerfree","id": 298921,"likes_rate": 82,"updated_date": 1446457672000,"app_type": "GAME","developer": {"email": "support@outfit7.com","id": 4286153,"name": "Outfit7"},"icons": {"px24": "http://img.wdjimg.com/mms/icon/v1/1/c8/e1e9126c136e18399204a1b738262c81_24_24.png","px36": "http://img.wdjimg.com/mms/icon/v1/1/c8/e1e9126c136e18399204a1b738262c81_36_36.png","px48": "http://img.wdjimg.com/mms/icon/v1/1/c8/e1e9126c136e18399204a1b738262c81_48_48.png","px68": "http://img.wdjimg.com/mms/icon/v1/1/c8/e1e9126c136e18399204a1b738262c81_68_68.png","px78": "http://img.wdjimg.com/mms/icon/v1/1/c8/e1e9126c136e18399204a1b738262c81_78_78.png","px100": "http://img.wdjimg.com/mms/icon/v1/1/c8/e1e9126c136e18399204a1b738262c81_100_100.png","px256": "http://img.wdjimg.com/mms/icon/v1/1/c8/e1e9126c136e18399204a1b738262c81_256_256.png"},"categories": [{"alias": "casual","level": 1,"name": "休闲时间","type": "GAME"},{"level": 2,"name": "益智","type": "GAME"}],"title_en": "Talking Ginger","alias": "Talking Ginger"}},"action": {"intent": "wdj://games/com.outfit7.talkinggingerfree?pageName=ClassicTopsPage&cardName=AppGameRankWithNumber&feedItemId=com.outfit7.talkinggingerfree","url": "http://apis.wandoujia.com/five/v2/apps/com.outfit7.talkinggingerfree?pos=m%2Ftops%2FClassicTopsPage%2FAppGameRankWithNumber%2FAPP&udid="},"badge": 256,"symbol": "258.","content_type": "APP","template_type": "SINGLE_TALL","id_string": "AppGameRankWithNumber:com.outfit7.talkinggingerfree","tag_line": "46.9MB","icon_image": {"url": "http://img.wdjimg.com/mms/icon/v1/1/c8/e1e9126c136e18399204a1b738262c81_256_256.png"},"strategy_name": "ClassicTopsPage"},{"icon": "http://img.wdjimg.com/mms/icon/v1/c/67/0ab1fb7a157738a91d1409290fbf767c_256_256.png","title": "in","sub_title": "42.6MB","detail": {"app_detail": {"ad": true,"detail_param": "isAds=true&token=EyUQQO0os4hhOsijU3F7Etw10m7ebxDkOO7_S-7pTj8REhtzbzz9FBZFdqgG8vTJtkut5ZSZw011bL2memJT2A&adsPos=packageAds%2F/1&source=&sid=0d2efe0fe8b74335970264d4ae7b76b01470310992181&sToken=Wyt8YyCH8_sKU7HfQgfkRbBci1-2MrFzBnbm2rq2u6BH3giua4qcuKrA4L-f9x2CDFVd12kQLRzEWpPT2sYw9w&bucketId=bi-plutus-cnc5.hlg01.wandoujia.com&testTag=plutus&adwordId=19&pn=com.jiuyan.infashion&bid=1193680&isAds=true&pos=m%2Ftops%2FClassicTopsPage%2FAppGameRankWithNumber%2FAPP&udid=","apk": [{"ads_type": "NONE","beta": false,"bytes_": 44701242,"download_url": {"aggr_weight": 300,"market": "官方","refer_url": "http://apps.wandoujia.com/apps/com.jiuyan.infashion?uid=8958993","url": "http://apps.wandoujia.com/redirect?signature=0799e28&url=http%3A%2F%2Fapk.wandoujia.com%2Fe%2Fe7%2F0d019883812c91b8d9ad395aa7a0de7e.apk&pn=com.jiuyan.infashion&md5=0d019883812c91b8d9ad395aa7a0de7e&apkid=19069400&vc=69&size=44701242&pos=m%2Ftops%2FClassicTopsPage%2FAppGameRankWithNumber%2FAPP&udid="},"size": "42.63M","version_code": 69,"version_name": "2.9.6","security_status": "UNKNOWN","md5": "0d019883812c91b8d9ad395aa7a0de7e","resolution": ["mdpi","hdpi","xhdpi","xxhdpi","xxxhdpi"],"permission_level": "TRUSTED","verified": 2,"superior": 0,"compatible": 1,"paid_type": "NONE","creation": 1470106017000}],"title": "in","comments_count": 1927,"likes_count": 2605,"dislikes_count": 321,"editor_comment": "海量贴纸，轻松让你一秒变自拍大师","installed_count_str": "337 万","package_name": "com.jiuyan.infashion","id": 2290294,"likes_rate": 89,"banner": "http://img.wdjimg.com/mms/banner/6/ba/8c531cd001a5880814cb5cb0bc546ba6_300_250.jpeg","updated_date": 1470106094000,"impr_url": "http://click.wandoujia.com/static/uploads/i/com.jiuyan.infashion/15705/1193680.gif?bid=1193680&adsPos=packageAds%2F/1&source=&sid=0d2efe0fe8b74335970264d4ae7b76b01470310992181&sToken=Wyt8YyCH8_sKU7HfQgfkRbBci1-2MrFzBnbm2rq2u6BH3giua4qcuKrA4L-f9x2CDFVd12kQLRzEWpPT2sYw9w&bucketId=bi-plutus-cnc5.hlg01.wandoujia.com&testTag=plutus&adwordId=19&pn=com.jiuyan.infashion&token=EyUQQO0os4hhOsijU3F7Etw10m7ebxDkOO7_S-7pTj8REhtzbzz9FBZFdqgG8vTJtkut5ZSZw011bL2memJT2A&pos=m%2Ftops%2FClassicTopsPage%2FAppGameRankWithNumber%2FAPP","app_type": "APP","developer": {"email": "in@in66.com","id": 8958993,"name": "杭州九言科技股份有限公司"},"icons": {"px24": "http://img.wdjimg.com/mms/icon/v1/c/67/0ab1fb7a157738a91d1409290fbf767c_24_24.png","px36": "http://img.wdjimg.com/mms/icon/v1/c/67/0ab1fb7a157738a91d1409290fbf767c_36_36.png","px48": "http://img.wdjimg.com/mms/icon/v1/c/67/0ab1fb7a157738a91d1409290fbf767c_48_48.png","px68": "http://img.wdjimg.com/mms/icon/v1/c/67/0ab1fb7a157738a91d1409290fbf767c_68_68.png","px78": "http://img.wdjimg.com/mms/icon/v1/c/67/0ab1fb7a157738a91d1409290fbf767c_78_78.png","px100": "http://img.wdjimg.com/mms/icon/v1/c/67/0ab1fb7a157738a91d1409290fbf767c_100_100.png","px256": "http://img.wdjimg.com/mms/icon/v1/c/67/0ab1fb7a157738a91d1409290fbf767c_256_256.png"},"categories": [{"alias": "picture","level": 1,"name": "图像","type": "APP"},{"level": 2,"name": "图片分享","type": "APP"},{"level": 2,"name": "相机","type": "APP"}],"title_en": " ","alias": "IN-大头美图相机，in美图"}},"action": {"intent": "wdj://apps/com.jiuyan.infashion?pageName=ClassicTopsPage&cardName=AppGameRankWithNumber&feedItemId=com.jiuyan.infashion","url": "http://apis.wandoujia.com/five/v2/apps/com.jiuyan.infashion?isAds=true&token=EyUQQO0os4hhOsijU3F7Etw10m7ebxDkOO7_S-7pTj8REhtzbzz9FBZFdqgG8vTJtkut5ZSZw011bL2memJT2A&adsPos=packageAds%2F/1&source=&sid=0d2efe0fe8b74335970264d4ae7b76b01470310992181&sToken=Wyt8YyCH8_sKU7HfQgfkRbBci1-2MrFzBnbm2rq2u6BH3giua4qcuKrA4L-f9x2CDFVd12kQLRzEWpPT2sYw9w&bucketId=bi-plutus-cnc5.hlg01.wandoujia.com&testTag=plutus&adwordId=19&pn=com.jiuyan.infashion&bid=1193680&isAds=true&pos=m%2Ftops%2FClassicTopsPage%2FAppGameRankWithNumber%2FAPP&udid="},"badge": 288,"symbol": "259.","content_type": "APP","template_type": "SINGLE_TALL","id_string": "AppGameRankWithNumber:com.jiuyan.infashion","tag_line": "42.6MB","icon_image": {"url": "http://img.wdjimg.com/mms/icon/v1/c/67/0ab1fb7a157738a91d1409290fbf767c_256_256.png","rgbs": -632764},"strategy_name": "ClassicTopsPage"}]}