{"next_url": "http://startpage.wandoujia.com/five/v3/tabs/tops?start=425&max=5&sessionId=7598048721385334827&pos=m%2Ftops","pre_url": "http://startpage.wandoujia.com/five/v3/tabs/tops?start=415&max=5&sessionId=7598048721385334827&pos=m%2Ftops","has_more": true,"pb_version": 0,"session_id": 7598048721385334827,"status": 200,"entity": [{"icon": "http://img.wdjimg.com/mms/icon/v1/f/e1/91b3f9a26db8cbdce7e1b890c8f1ae1f_256_256.png","title": "台球大师","sub_title": "3.1MB","detail": {"app_detail": {"ad": false,"detail_param": "pos=m%2Ftops%2FClassicTopsPage%2FAppGameRankWithNumber%2FAPP&udid=","apk": [{"ads_type": "EMBEDED","beta": false,"bytes_": 3252260,"download_url": {"aggr_weight": 300,"market": "官方","refer_url": "http://apps.wandoujia.com/apps/com.forthblue.pool?uid=197749888","url": "http://apps.wandoujia.com/redirect?signature=816a526&url=http%3A%2F%2Fapk.wandoujia.com%2Fd%2Fb6%2F405ad9ac380a25912928ba2b32f96b6d.apk&pn=com.forthblue.pool&md5=405ad9ac380a25912928ba2b32f96b6d&apkid=19084682&vc=123456780&size=3252260&pos=m%2Ftops%2FClassicTopsPage%2FAppGameRankWithNumber%2FAPP&udid="},"size": "3.1M","version_code": 123456780,"version_name": "4.1.0","security_status": "UNKNOWN","md5": "405ad9ac380a25912928ba2b32f96b6d","resolution": ["ldpi","mdpi","hdpi"],"permission_level": "NORMAL","verified": 2,"superior": 0,"compatible": 1,"paid_type": "NONE","creation": 1470238658000}],"title": "台球大师","comments_count": 385,"likes_count": 359,"dislikes_count": 145,"installed_count_str": "505 万","package_name": "com.forthblue.pool","id": 9834,"likes_rate": 71,"updated_date": 1470296760000,"app_type": "GAME","developer": {"email": "support@terrandroid.com","id": 197749888,"name": "北京重力无限科技有限公司"},"icons": {"px24": "http://img.wdjimg.com/mms/icon/v1/f/e1/91b3f9a26db8cbdce7e1b890c8f1ae1f_24_24.png","px36": "http://img.wdjimg.com/mms/icon/v1/f/e1/91b3f9a26db8cbdce7e1b890c8f1ae1f_36_36.png","px48": "http://img.wdjimg.com/mms/icon/v1/f/e1/91b3f9a26db8cbdce7e1b890c8f1ae1f_48_48.png","px68": "http://img.wdjimg.com/mms/icon/v1/f/e1/91b3f9a26db8cbdce7e1b890c8f1ae1f_68_68.png","px78": "http://img.wdjimg.com/mms/icon/v1/f/e1/91b3f9a26db8cbdce7e1b890c8f1ae1f_78_78.png","px100": "http://img.wdjimg.com/mms/icon/v1/f/e1/91b3f9a26db8cbdce7e1b890c8f1ae1f_100_100.png","px256": "http://img.wdjimg.com/mms/icon/v1/f/e1/91b3f9a26db8cbdce7e1b890c8f1ae1f_256_256.png"},"categories": [{"alias": "sports","level": 1,"name": "体育格斗","type": "GAME"},{"level": 2,"name": "台球","type": "GAME"}],"title_en": "Pool Master Pro","alias": "Pool Master Pro,台球poolmasterpro,台球 pool master pro"}},"action": {"intent": "wdj://games/com.forthblue.pool?pageName=ClassicTopsPage&cardName=AppGameRankWithNumber&feedItemId=com.forthblue.pool","url": "http://apis.wandoujia.com/five/v2/apps/com.forthblue.pool?pos=m%2Ftops%2FClassicTopsPage%2FAppGameRankWithNumber%2FAPP&udid="},"badge": 0,"symbol": "420.","content_type": "APP","template_type": "SINGLE_TALL","id_string": "AppGameRankWithNumber:com.forthblue.pool","tag_line": "3.1MB","icon_image": {"url": "http://img.wdjimg.com/mms/icon/v1/f/e1/91b3f9a26db8cbdce7e1b890c8f1ae1f_256_256.png"},"strategy_name": "ClassicTopsPage"},{"icon": "http://img.wdjimg.com/mms/icon/v1/2/41/dac2ff6fca2d898aede39b15de665412_256_256.png","title": "MX Player 解码包 (ARMv7 NEON)","sub_title": "6.0MB","detail": {"app_detail": {"ad": false,"detail_param": "pos=m%2Ftops%2FClassicTopsPage%2FAppGameRankWithNumber%2FAPP&udid=","apk": [{"ads_type": "NONE","beta": false,"bytes_": 6245895,"download_url": {"aggr_weight": 1,"market": "应用汇","refer_url": "http://www.appchina.com/app/com.mxtech.ffmpeg.v7_neon","url": "http://apps.wandoujia.com/redirect?signature=fe54832&url=http%3A%2F%2Fmobile.d.appchina.com%2FMcDonald%2Fr%2F2847192%2Fcom.mxtech.ffmpeg.v7_neon_85.vapk%3Fc%3Daplus.direct%26m%3Dredirect%26p%3Daplus.detail%26page%3Dappplus.detail%26ref%26uid%3D0&pn=com.mxtech.ffmpeg.v7_neon&md5=b9c23b13d06df46bf529be6a7c565bbe&apkid=14650066&vc=85&size=6245895&pos=m%2Ftops%2FClassicTopsPage%2FAppGameRankWithNumber%2FAPP&udid="},"size": "5.96M","version_code": 85,"version_name": "1.7.39","security_status": "SAFE","md5": "b9c23b13d06df46bf529be6a7c565bbe","security_detail": [{"provider": "360","status": "SAFE"},{"provider": "tencent","status": "SAFE"},{"provider": "lbe","status": "SAFE"}],"resolution": ["mdpi","hdpi","xhdpi"],"permission_level": "NORMAL","verified": 3,"superior": 0,"compatible": 1,"paid_type": "NONE","creation": 1434054104000}],"title": "MX Player 解码包 (ARMv7 NEON)","comments_count": 111,"likes_count": 65,"dislikes_count": 60,"installed_count_str": "139 万","package_name": "com.mxtech.ffmpeg.v7_neon","id": 135895,"likes_rate": 52,"updated_date": 1355995866000,"app_type": "APP","developer": {"email": "mxvideoplayer@gmail.com","id": 0,"name": "Google Play提供"},"icons": {"px24": "http://img.wdjimg.com/mms/icon/v1/2/41/dac2ff6fca2d898aede39b15de665412_24_24.png","px36": "http://img.wdjimg.com/mms/icon/v1/2/41/dac2ff6fca2d898aede39b15de665412_36_36.png","px48": "http://img.wdjimg.com/mms/icon/v1/2/41/dac2ff6fca2d898aede39b15de665412_48_48.png","px68": "http://img.wdjimg.com/mms/icon/v1/2/41/dac2ff6fca2d898aede39b15de665412_68_68.png","px78": "http://img.wdjimg.com/mms/icon/v1/2/41/dac2ff6fca2d898aede39b15de665412_78_78.png","px100": "http://img.wdjimg.com/mms/icon/v1/2/41/dac2ff6fca2d898aede39b15de665412_100_100.png","px256": "http://img.wdjimg.com/mms/icon/v1/2/41/dac2ff6fca2d898aede39b15de665412_256_256.png"},"categories": [{"alias": "video","level": 1,"name": "视频","type": "APP"},{"level": 2,"name": "视频播放器","type": "APP"}],"alias": "Mx播放器解码包 Player Codec ARMv7 NEON Android_com.mxtech.ffmpeg.v7_neon"}},"action": {"intent": "wdj://apps/com.mxtech.ffmpeg.v7_neon?pageName=ClassicTopsPage&cardName=AppGameRankWithNumber&feedItemId=com.mxtech.ffmpeg.v7_neon","url": "http://apis.wandoujia.com/five/v2/apps/com.mxtech.ffmpeg.v7_neon?pos=m%2Ftops%2FClassicTopsPage%2FAppGameRankWithNumber%2FAPP&udid="},"badge": 256,"symbol": "421.","content_type": "APP","template_type": "SINGLE_TALL","id_string": "AppGameRankWithNumber:com.mxtech.ffmpeg.v7_neon","tag_line": "6.0MB","icon_image": {"url": "http://img.wdjimg.com/mms/icon/v1/2/41/dac2ff6fca2d898aede39b15de665412_256_256.png"},"strategy_name": "ClassicTopsPage"},{"icon": "http://img.wdjimg.com/mms/icon/v1/3/50/86dce14d2a5b4ba427744c0aaf07e503_256_256.png","title": "有信电话","sub_title": "22.3MB","detail": {"app_detail": {"ad": false,"detail_param": "pos=m%2Ftops%2FClassicTopsPage%2FAppGameRankWithNumber%2FAPP&udid=","apk": [{"ads_type": "EMBEDED","beta": false,"bytes_": 23349142,"download_url": {"aggr_weight": 300,"market": "官方","refer_url": "http://apps.wandoujia.com/apps/com.yx?uid=3260524","url": "http://apps.wandoujia.com/redirect?signature=1b84ae9&url=http%3A%2F%2Fapk.wandoujia.com%2F5%2F17%2Ff9e6186fb2d92c7db4bfe92280aee175.apk&pn=com.yx&md5=f9e6186fb2d92c7db4bfe92280aee175&apkid=19088276&vc=4161&size=23349142&pos=m%2Ftops%2FClassicTopsPage%2FAppGameRankWithNumber%2FAPP&udid="},"size": "22.27M","version_code": 4161,"version_name": "5.2.3","security_status": "UNKNOWN","md5": "f9e6186fb2d92c7db4bfe92280aee175","resolution": ["mdpi","hdpi","xhdpi","xxhdpi"],"permission_level": "TRUSTED","verified": 3,"superior": 0,"compatible": 1,"paid_type": "NONE","creation": 1470270568000}],"title": "有信电话","comments_count": 7445,"likes_count": 7962,"dislikes_count": 837,"editor_comment": "支持在 Wifi、3G 网络下与好友免费通话，是情侣、朋友、家人间的聊天神器。","installed_count_str": "911 万","package_name": "com.yx","id": 23354,"likes_rate": 90,"updated_date": 1470270654000,"app_type": "APP","developer": {"email": "uxin2015@uxin.com","id": 3260524,"name": "深圳市有信网络技术有限公司"},"icons": {"px24": "http://img.wdjimg.com/mms/icon/v1/3/50/86dce14d2a5b4ba427744c0aaf07e503_24_24.png","px36": "http://img.wdjimg.com/mms/icon/v1/3/50/86dce14d2a5b4ba427744c0aaf07e503_36_36.png","px48": "http://img.wdjimg.com/mms/icon/v1/3/50/86dce14d2a5b4ba427744c0aaf07e503_48_48.png","px68": "http://img.wdjimg.com/mms/icon/v1/3/50/86dce14d2a5b4ba427744c0aaf07e503_68_68.png","px78": "http://img.wdjimg.com/mms/icon/v1/3/50/86dce14d2a5b4ba427744c0aaf07e503_78_78.png","px100": "http://img.wdjimg.com/mms/icon/v1/3/50/86dce14d2a5b4ba427744c0aaf07e503_100_100.png","px256": "http://img.wdjimg.com/mms/icon/v1/3/50/86dce14d2a5b4ba427744c0aaf07e503_256_256.png"},"categories": [{"alias": "mobile","level": 1,"name": "电话通讯","type": "APP"},{"level": 2,"name": "电话","type": "APP"}],"title_en": " ","alias": "有信"}},"action": {"intent": "wdj://apps/com.yx?pageName=ClassicTopsPage&cardName=AppGameRankWithNumber&feedItemId=com.yx","url": "http://apis.wandoujia.com/five/v2/apps/com.yx?pos=m%2Ftops%2FClassicTopsPage%2FAppGameRankWithNumber%2FAPP&udid="},"badge": 256,"symbol": "422.","content_type": "APP","template_type": "SINGLE_TALL","id_string": "AppGameRankWithNumber:com.yx","tag_line": "22.3MB","icon_image": {"url": "http://img.wdjimg.com/mms/icon/v1/3/50/86dce14d2a5b4ba427744c0aaf07e503_256_256.png"},"strategy_name": "ClassicTopsPage"},{"icon": "http://img.wdjimg.com/mms/icon/v1/b/6e/3233523a9aed775876f73a3c037626eb_256_256.png","title": "360免费WiFi","sub_title": "7.7MB","detail": {"app_detail": {"ad": false,"detail_param": "pos=m%2Ftops%2FClassicTopsPage%2FAppGameRankWithNumber%2FAPP&udid=","apk": [{"ads_type": "NONE","beta": false,"bytes_": 8099614,"download_url": {"aggr_weight": 2,"market": "360手机助手","refer_url": "http://123.125.82.206/mintf/getAppInfoByIds?pname=com.qihoo.freewifi","url": "http://apps.wandoujia.com/redirect?signature=9e229b7&url=http%3A%2F%2Fm.shouji.360tpcdn.com%2F160804%2Fd6dd0c930e4fa059a42cf67511ffcf35%2Fcom.qihoo.freewifi_390.apk&pn=com.qihoo.freewifi&md5=d6dd0c930e4fa059a42cf67511ffcf35&apkid=19092046&vc=390&size=8099614&pos=m%2Ftops%2FClassicTopsPage%2FAppGameRankWithNumber%2FAPP&udid="},"size": "7.72M","version_code": 390,"version_name": "3.9.0","security_status": "UNKNOWN","md5": "d6dd0c930e4fa059a42cf67511ffcf35","resolution": ["mdpi","hdpi","xhdpi","xxhdpi"],"permission_level": "TRUSTED","verified": 2,"superior": 0,"compatible": 1,"paid_type": "NONE","creation": 1470281911000}],"title": "360免费WiFi","comments_count": 6673,"likes_count": 7736,"dislikes_count": 357,"editor_comment": "连接免费 WiFi 可能带来隐私风险","installed_count_str": "678 万","package_name": "com.qihoo.freewifi","id": 2432710,"likes_rate": 96,"updated_date": 1464327871000,"app_type": "APP","developer": {"id": 100904139,"name": "侯淇元"},"icons": {"px24": "http://img.wdjimg.com/mms/icon/v1/b/6e/3233523a9aed775876f73a3c037626eb_24_24.png","px36": "http://img.wdjimg.com/mms/icon/v1/b/6e/3233523a9aed775876f73a3c037626eb_36_36.png","px48": "http://img.wdjimg.com/mms/icon/v1/b/6e/3233523a9aed775876f73a3c037626eb_48_48.png","px68": "http://img.wdjimg.com/mms/icon/v1/b/6e/3233523a9aed775876f73a3c037626eb_68_68.png","px78": "http://img.wdjimg.com/mms/icon/v1/b/6e/3233523a9aed775876f73a3c037626eb_78_78.png","px100": "http://img.wdjimg.com/mms/icon/v1/b/6e/3233523a9aed775876f73a3c037626eb_100_100.png","px256": "http://img.wdjimg.com/mms/icon/v1/b/6e/3233523a9aed775876f73a3c037626eb_256_256.png"},"categories": [{"alias": "optimization","level": 1,"name": "系统工具","type": "APP"},{"level": 2,"name": "Wi-Fi","type": "APP"}],"title_en": " ","alias": "360免费WiFi Android_com.qihoo.freewifi"}},"action": {"intent": "wdj://apps/com.qihoo.freewifi?pageName=ClassicTopsPage&cardName=AppGameRankWithNumber&feedItemId=com.qihoo.freewifi","url": "http://apis.wandoujia.com/five/v2/apps/com.qihoo.freewifi?pos=m%2Ftops%2FClassicTopsPage%2FAppGameRankWithNumber%2FAPP&udid="},"badge": 256,"symbol": "423.","content_type": "APP","template_type": "SINGLE_TALL","id_string": "AppGameRankWithNumber:com.qihoo.freewifi","tag_line": "7.7MB","icon_image": {"url": "http://img.wdjimg.com/mms/icon/v1/b/6e/3233523a9aed775876f73a3c037626eb_256_256.png"},"strategy_name": "ClassicTopsPage"},{"icon": "http://img.wdjimg.com/mms/icon/v1/8/de/3707b2a9c2c088e839e17a33e726cde8_256_256.png","title": "全民飞机大战","sub_title": "168.0MB","detail": {"app_detail": {"ad": false,"detail_param": "pos=m%2Ftops%2FClassicTopsPage%2FAppGameRankWithNumber%2FAPP&udid=","apk": [{"ads_type": "NONE","beta": false,"bytes_": 176121115,"download_url": {"aggr_weight": 2,"market": "360手机助手","refer_url": "http://123.125.82.206/mintf/getAppInfoByIds?pname=com.tencent.feiji","url": "http://apps.wandoujia.com/redirect?signature=77d4f75&url=http%3A%2F%2Fm.shouji.360tpcdn.com%2F160708%2Fba0d5e194d0cb631f4d7df35149b09c2%2Fcom.tencent.feiji_45.apk&pn=com.tencent.feiji&md5=ba0d5e194d0cb631f4d7df35149b09c2&apkid=18837814&vc=45&size=176121115&pos=m%2Ftops%2FClassicTopsPage%2FAppGameRankWithNumber%2FAPP&udid="},"size": "167.96M","version_code": 45,"version_name": "1.0.44","security_status": "UNKNOWN","md5": "ba0d5e194d0cb631f4d7df35149b09c2","resolution": ["ldpi","mdpi","hdpi","xhdpi","xxhdpi"],"permission_level": "TRUSTED","verified": 2,"superior": 0,"compatible": 1,"paid_type": "NONE","creation": 1468008198000}],"title": "全民飞机大战","comments_count": 1762,"likes_count": 1653,"dislikes_count": 904,"installed_count_str": "2094 万","package_name": "com.tencent.feiji","id": 1470285,"likes_rate": 65,"updated_date": 1433387131000,"app_type": "GAME","developer": {"id": 102264635,"name": "深圳市腾讯计算机系统有限公司"},"icons": {"px24": "http://img.wdjimg.com/mms/icon/v1/8/de/3707b2a9c2c088e839e17a33e726cde8_24_24.png","px36": "http://img.wdjimg.com/mms/icon/v1/8/de/3707b2a9c2c088e839e17a33e726cde8_36_36.png","px48": "http://img.wdjimg.com/mms/icon/v1/8/de/3707b2a9c2c088e839e17a33e726cde8_48_48.png","px68": "http://img.wdjimg.com/mms/icon/v1/8/de/3707b2a9c2c088e839e17a33e726cde8_68_68.png","px78": "http://img.wdjimg.com/mms/icon/v1/8/de/3707b2a9c2c088e839e17a33e726cde8_78_78.png","px100": "http://img.wdjimg.com/mms/icon/v1/8/de/3707b2a9c2c088e839e17a33e726cde8_100_100.png","px256": "http://img.wdjimg.com/mms/icon/v1/8/de/3707b2a9c2c088e839e17a33e726cde8_256_256.png"},"categories": [{"alias": "shooting","level": 1,"name": "动作射击","type": "GAME"},{"level": 2,"name": "飞行","type": "GAME"}],"title_en": " ","alias": "全民飞机大战豪华版,全名飞机,全名飞机大战,全民打飞机,全民飞机大战更新"}},"action": {"intent": "wdj://games/com.tencent.feiji?pageName=ClassicTopsPage&cardName=AppGameRankWithNumber&feedItemId=com.tencent.feiji","url": "http://apis.wandoujia.com/five/v2/apps/com.tencent.feiji?pos=m%2Ftops%2FClassicTopsPage%2FAppGameRankWithNumber%2FAPP&udid="},"badge": 256,"symbol": "424.","content_type": "APP","template_type": "SINGLE_TALL","id_string": "AppGameRankWithNumber:com.tencent.feiji","tag_line": "168.0MB","icon_image": {"url": "http://img.wdjimg.com/mms/icon/v1/8/de/3707b2a9c2c088e839e17a33e726cde8_256_256.png"},"strategy_name": "ClassicTopsPage"}]}